pipelined/rtl/pipe_reg.v
// pipe_reg.v — a generic pipeline register (the "divider" between stages)
// Carries WIDTH bits of data from one stage to the next on each clock.
module pipe_reg #(
    parameter WIDTH = 32
)(
    input  wire              clk,
    input  wire              rst_n,
    input  wire              en,      // 1 = update, 0 = stall (hold value)
    input  wire              clear,   // 1 = flush (wipe to 0 / NOP)
    input  wire [WIDTH-1:0]  d,       // data in (from current stage)
    output reg  [WIDTH-1:0]  q         // data out (to next stage)
);
    always @(posedge clk or negedge rst_n) begin
        if (!rst_n)      q <= {WIDTH{1'b0}};   // reset: clear
        else if (clear)  q <= {WIDTH{1'b0}};   // flush: wipe to NOP
        else if (en)     q <= d;               // normal: pass data forward
        // if en==0 and not clearing: HOLD (stall) — q keeps its value
    end
endmodule

pipelined/tb/pipe_reg_tb.v
module pipe_reg_tb;
    reg clk, rst_n, en, clear;
    reg  [7:0] d;
    wire [7:0] q;

    pipe_reg #(.WIDTH(8)) dut (.clk(clk), .rst_n(rst_n),
        .en(en), .clear(clear), .d(d), .q(q));

    always #5 clk = ~clk;

    initial begin
        $dumpfile("pipe_reg.vcd"); $dumpvars(0, pipe_reg_tb);
        clk=0; rst_n=0; en=1; clear=0; d=0;
        #10 rst_n=1;

        d=8'd11; en=1; clear=0; #10;  $display("normal: d=11 -> q=%0d (expect 11)", q);
        d=8'd22; en=0; clear=0; #10;  $display("stall:  d=22 en=0 -> q=%0d (expect still 11)", q);
        d=8'd33; en=1; clear=0; #10;  $display("normal: d=33 -> q=%0d (expect 33)", q);
        d=8'd44; en=1; clear=1; #10;  $display("flush:  clear=1 -> q=%0d (expect 0)", q);
        $finish;
    end
endmodule

pipelined/pipe_reg.vcd
$date
	Sat Jun 20 00:49:52 2026
$end
$version
	Icarus Verilog
$end
$timescale
	1s
$end
$scope module pipe_reg_tb $end
$var wire 8 ! q [7:0] $end
$var reg 1 " clear $end
$var reg 1 # clk $end
$var reg 8 $ d [7:0] $end
$var reg 1 % en $end
$var reg 1 & rst_n $end
$scope module dut $end
$var wire 1 " clear $end
$var wire 1 # clk $end
$var wire 8 ' d [7:0] $end
$var wire 1 % en $end
$var wire 1 & rst_n $end
$var parameter 32 ( WIDTH $end
$var reg 8 ) q [7:0] $end
$upscope $end
$upscope $end
$enddefinitions $end
$comment Show the parameter values. $end
$dumpall
b1000 (
$end
#0
$dumpvars
b0 )
b0 '
0&
1%
b0 $
0#
0"
b0 !
$end
#5
1#
#10
0#
b1011 $
b1011 '
1&
#15
b1011 !
b1011 )
1#
#20
0#
0%
b10110 $
b10110 '
#25
1#
#30
0#
1%
b100001 $
b100001 '
#35
b100001 !
b100001 )
1#
#40
0#
1"
b101100 $
b101100 '
#45
b0 !
b0 )
1#
