pipelined/rtl/dmem.v
// dmem.v — simple data memory for loads and stores
module dmem (
    input  wire        clk,
    input  wire        mem_read,
    input  wire        mem_write,
    input  wire [31:0] addr,
    input  wire [31:0] write_data,
    output wire [31:0] read_data
);
    reg [31:0] mem [0:63];   // 64 words of data memory

    // preload some test values
    integer i;
    initial begin
        for (i = 0; i < 64; i = i + 1) mem[i] = 32'd0;
        mem[0] = 32'd100;    // memory[0] = 100
        mem[1] = 32'd200;    // memory[1] = 200
    end

    // write on clock edge
    always @(posedge clk) begin
        if (mem_write) mem[addr[31:2]] <= write_data;
    end

    // read is combinational
    assign read_data = mem_read ? mem[addr[31:2]] : 32'd0;
endmodule

single_cycle/rtl/alu.v
// alu.v — Arithmetic Logic Unit for RV32I
module alu (
    input  wire [31:0] a,          // first operand
    input  wire [31:0] b,          // second operand
    input  wire [3:0]  alu_op,     // which operation to perform
    output reg  [31:0] result,     // the answer
    output wire        zero        // 1 if result == 0 (used by branches later)
);
    always @(*) begin              // combinational: recompute whenever inputs change
        case (alu_op)
            4'd0: result = a + b;                         // ADD
            4'd1: result = a - b;                         // SUB
            4'd2: result = a & b;                         // AND
            4'd3: result = a | b;                         // OR
            4'd4: result = a ^ b;                         // XOR
            4'd5: result = ($signed(a) < $signed(b)) ? 32'd1 : 32'd0;  // SLT
            4'd6: result = a << b[4:0];                   // shift left
            4'd7: result = a >> b[4:0];                   // shift right
            default: result = 32'd0;
        endcase
    end

    assign zero = (result == 32'd0);   // flag: is the result zero?
endmodule

pipelined/rtl/forwarding.v
// forwarding.v — decides whether to forward ALU operands from later stages
module forwarding (
    input  wire [4:0] ex_rs1,        // source reg 1 needed in EX
    input  wire [4:0] ex_rs2,        // source reg 2 needed in EX
    input  wire [4:0] mem_rd,        // dest reg of instr in MEM stage
    input  wire       mem_reg_write, // does MEM-stage instr write a reg?
    input  wire [4:0] wb_rd,         // dest reg of instr in WB stage
    input  wire       wb_reg_write,  // does WB-stage instr write a reg?
    output reg  [1:0] forward_a,     // control for ALU input A
    output reg  [1:0] forward_b      // control for ALU input B
);
    // 2'b00 = use register file value (normal)
    // 2'b10 = forward from MEM stage (freshest)
    // 2'b01 = forward from WB stage
    always @(*) begin
        // ---- Forward A (for rs1) ----
        if (mem_reg_write && mem_rd != 0 && mem_rd == ex_rs1)
            forward_a = 2'b10;                 // MEM forward (priority)
        else if (wb_reg_write && wb_rd != 0 && wb_rd == ex_rs1)
            forward_a = 2'b01;                 // WB forward
        else
            forward_a = 2'b00;                 // no forward

        // ---- Forward B (for rs2) ----
        if (mem_reg_write && mem_rd != 0 && mem_rd == ex_rs2)
            forward_b = 2'b10;
        else if (wb_reg_write && wb_rd != 0 && wb_rd == ex_rs2)
            forward_b = 2'b01;
        else
            forward_b = 2'b00;
    end
endmodule

pipelined/rtl/hazard.v
// hazard.v — detects load-use hazard, generates stall signal
module hazard (
    input  wire        ex_mem_read,  // is the instr in EX a load?
    input  wire [4:0]  ex_rd,        // dest reg of the load in EX
    input  wire [4:0]  id_rs1,       // source regs of instr in ID
    input  wire [4:0]  id_rs2,
    output reg         stall          // 1 = freeze pipeline one cycle
);
    always @(*) begin
        // load in EX, and the ID instruction needs its result -> stall
        if (ex_mem_read && ex_rd != 0 &&
            (ex_rd == id_rs1 || ex_rd == id_rs2))
            stall = 1'b1;
        else
            stall = 1'b0;
    end
endmodule

pipelined/rtl/immgen.v
// immgen.v — Immediate Generator: extracts & sign-extends immediates
module immgen (
    input  wire [31:0] instr,      // the full 32-bit instruction
    input  wire [2:0]  imm_type,   // which format: 0=I,1=S,2=B,3=U,4=J
    output reg  [31:0] imm          // the reconstructed 32-bit immediate
);
    always @(*) begin
        case (imm_type)
            // I-type (e.g. addi, loads): imm is bits [31:20]
            3'd0: imm = {{20{instr[31]}}, instr[31:20]};

            // S-type (stores): imm split across [31:25] and [11:7]
            3'd1: imm = {{20{instr[31]}}, instr[31:25], instr[11:7]};

            // B-type (branches): imm scattered, lowest bit always 0
            3'd2: imm = {{19{instr[31]}}, instr[31], instr[7],
                         instr[30:25], instr[11:8], 1'b0};

            // U-type (lui, auipc): imm is the upper 20 bits, shifted
            3'd3: imm = {instr[31:12], 12'b0};

            // J-type (jal): imm scattered, lowest bit always 0
            3'd4: imm = {{11{instr[31]}}, instr[31], instr[19:12],
                         instr[20], instr[30:21], 1'b0};

            default: imm = 32'd0;
        endcase
    end
endmodule

pipelined/rtl/regfile.v
// regfile.v — 32 x 32-bit register file, 2 read ports, 1 write port
module regfile (
    input  wire        clk,
    input  wire        we,          // write enable
    input  wire [4:0]  ra1,         // read address 1 (which locker to read)
    input  wire [4:0]  ra2,         // read address 2
    input  wire [4:0]  wa,          // write address (which locker to write)
    input  wire [31:0] wd,          // write data
    output wire [31:0] rd1,         // read data 1
    output wire [31:0] rd2          // read data 2
);
    // the 32 lockers, each 32 bits wide
    reg [31:0] regs [0:31];

    // WRITE: on the clock edge, if enabled and not writing to x0
    always @(negedge clk) begin
        if (we && wa != 5'd0)
            regs[wa] <= wd;
    end

    // READ: combinational (instant). x0 always reads as 0.
    assign rd1 = (ra1 == 5'd0) ? 32'd0 : regs[ra1];
    assign rd2 = (ra2 == 5'd0) ? 32'd0 : regs[ra2];
endmodule

single_cycle/rtl/control.v
// control.v — main decoder: reads opcode, sets control signals
module control (
    input  wire [6:0] opcode,      // bottom 7 bits of the instruction
    output reg        reg_write,   // write result to a register?
    output reg        alu_src,     // 1 = use immediate, 0 = use register
    output reg        mem_read,    // reading data memory?
    output reg        mem_write,   // writing data memory?
    output reg        branch,      // is this a branch?
    output reg  [1:0] imm_type     // which immediate format
);
    always @(*) begin
        // safe defaults (everything off)
        reg_write = 0; alu_src = 0; mem_read = 0;
        mem_write = 0; branch = 0; imm_type = 2'd0;

        case (opcode)
            7'b0110011: begin   // R-type (add, sub, and, or...) reg-reg
                reg_write = 1; alu_src = 0;
            end
            7'b0010011: begin   // I-type ALU (addi, andi...) reg-immediate
                reg_write = 1; alu_src = 1; imm_type = 2'd0;
            end
            7'b0000011: begin   // Load (lw): reg = mem[reg + imm]
                reg_write = 1; alu_src = 1; mem_read = 1; imm_type = 2'd0;
            end
            7'b0100011: begin   // Store (sw): mem[reg + imm] = reg
                alu_src = 1; mem_write = 1; imm_type = 2'd1;
            end
            7'b1100011: begin   // Branch (beq...)
                branch = 1; alu_src = 0; imm_type = 2'd2;
            end
            default: begin
                // unknown opcode: keep everything off
            end
        endcase
    end
endmodule

pipelined/rtl/pipeline_cpu.v
// pipeline_cpu.v — 5-stage RV32I: forwarding + loads/stores + load-use stall
module pipeline_cpu (
    input  wire clk,
    input  wire rst_n,
    output wire [31:0] pc_out,
    output wire [31:0] wb_data_out,
    output wire [4:0]  wb_rd_out,
    output wire        wb_we_out
);
    // ============ STAGE 1: IF ============
    reg [31:0] pc;
    wire stall;                              // from hazard unit
    wire [31:0] pc_next = pc + 32'd4;
    always @(posedge clk or negedge rst_n) begin
        if (!rst_n)      pc <= 32'd0;
        else if (stall)  pc <= pc;           // STALL: freeze PC
        else             pc <= pc_next;
    end
    assign pc_out = pc;

    reg [31:0] imem [0:15];
    initial begin
        // test program WITH a load-use hazard:
        imem[0] = 32'b000000000000_00000_010_00001_0000011; // lw  x1, 0(x0)   x1=mem[0]=100
        imem[1] = 32'b0000000_00001_00001_000_00010_0110011; // add x2, x1, x1  uses x1 RIGHT AFTER load!
        imem[2] = 32'b000000000101_00000_000_00011_0010011; // addi x3,x0,5
        imem[3] = 32'b0000000_00011_00010_000_00100_0110011; // add x4,x2,x3
        imem[4] = 32'd0;
    end
    wire [31:0] if_instr = imem[pc[31:2]];

    // ---- IF/ID register (can stall) ----
    reg [31:0] ID_pc, ID_instr;
    always @(posedge clk or negedge rst_n) begin
        if (!rst_n)      begin ID_pc <= 0; ID_instr <= 32'h00000013; end
        else if (stall)  begin ID_pc <= ID_pc; ID_instr <= ID_instr; end // STALL: hold
        else             begin ID_pc <= pc; ID_instr <= if_instr; end
    end

    // ============ STAGE 2: ID ============
    wire [6:0] id_opcode = ID_instr[6:0];
    wire [4:0] id_rs1 = ID_instr[19:15];
    wire [4:0] id_rs2 = ID_instr[24:20];
    wire [4:0] id_rd  = ID_instr[11:7];
    wire       id_funct7_5 = ID_instr[30];

    wire id_reg_write, id_alu_src, id_mem_read, id_mem_write, id_branch;
    wire [1:0] id_imm_type;
    control u_ctrl (.opcode(id_opcode), .reg_write(id_reg_write),
        .alu_src(id_alu_src), .mem_read(id_mem_read),
        .mem_write(id_mem_write), .branch(id_branch), .imm_type(id_imm_type));

    wire [31:0] id_rs1_data, id_rs2_data;
    regfile u_rf (.clk(clk), .we(wb_we_out),
        .ra1(id_rs1), .ra2(id_rs2), .wa(wb_rd_out), .wd(wb_data_out),
        .rd1(id_rs1_data), .rd2(id_rs2_data));

    wire [31:0] id_imm;
    immgen u_imm (.instr(ID_instr), .imm_type({1'b0, id_imm_type}), .imm(id_imm));
    wire [3:0] id_alu_op = (id_opcode == 7'b0110011 && id_funct7_5) ? 4'd1 : 4'd0;

    // ---- hazard detection (load-use) ----
    hazard u_hz (.ex_mem_read(EX_mem_read), .ex_rd(EX_rd),
        .id_rs1(id_rs1), .id_rs2(id_rs2), .stall(stall));

    // when stalling, insert a bubble: zero out the control signals into EX
    wire bubble = stall;

    // ---- ID/EX register ----
    reg [31:0] EX_rs1_data, EX_rs2_data, EX_imm;
    reg [4:0]  EX_rd, EX_rs1, EX_rs2;
    reg [3:0]  EX_alu_op;
    reg        EX_reg_write, EX_alu_src, EX_mem_read, EX_mem_write;
    always @(posedge clk or negedge rst_n) begin
        if (!rst_n) begin
            EX_reg_write<=0; EX_rd<=0; EX_alu_op<=0; EX_alu_src<=0;
            EX_rs1_data<=0; EX_rs2_data<=0; EX_imm<=0; EX_rs1<=0; EX_rs2<=0;
            EX_mem_read<=0; EX_mem_write<=0;
        end else begin
            EX_rs1_data  <= id_rs1_data;
            EX_rs2_data  <= id_rs2_data;
            EX_imm       <= id_imm;
            EX_rd        <= id_rd;
            EX_rs1       <= id_rs1;
            EX_rs2       <= id_rs2;
            EX_alu_op    <= id_alu_op;
            EX_alu_src   <= id_alu_src;
            // control signals: zeroed when bubble (stall) inserted
            EX_reg_write <= bubble ? 1'b0 : id_reg_write;
            EX_mem_read  <= bubble ? 1'b0 : id_mem_read;
            EX_mem_write <= bubble ? 1'b0 : id_mem_write;
        end
    end

    // ============ STAGE 3: EX (forwarding) ============
    wire [1:0] forward_a, forward_b;
    forwarding u_fwd (.ex_rs1(EX_rs1), .ex_rs2(EX_rs2),
        .mem_rd(MEM_rd), .mem_reg_write(MEM_reg_write),
        .wb_rd(WB_rd), .wb_reg_write(WB_reg_write),
        .forward_a(forward_a), .forward_b(forward_b));

    wire [31:0] ex_a = (forward_a==2'b10) ? MEM_alu_result :
                       (forward_a==2'b01) ? wb_data_out    : EX_rs1_data;
    wire [31:0] ex_b_pre = (forward_b==2'b10) ? MEM_alu_result :
                           (forward_b==2'b01) ? wb_data_out    : EX_rs2_data;
    wire [31:0] ex_alu_b = EX_alu_src ? EX_imm : ex_b_pre;

    wire [31:0] ex_alu_result;
    wire        ex_zero;
    alu u_alu (.a(ex_a), .b(ex_alu_b), .alu_op(EX_alu_op),
        .result(ex_alu_result), .zero(ex_zero));

    // ---- EX/MEM register ----
    reg [31:0] MEM_alu_result, MEM_write_data;
    reg [4:0]  MEM_rd;
    reg        MEM_reg_write, MEM_mem_read, MEM_mem_write;
    always @(posedge clk or negedge rst_n) begin
        if (!rst_n) begin
            MEM_reg_write<=0; MEM_rd<=0; MEM_alu_result<=0;
            MEM_mem_read<=0; MEM_mem_write<=0; MEM_write_data<=0;
        end else begin
            MEM_alu_result <= ex_alu_result;
            MEM_write_data <= ex_b_pre;        // store data (forwarded)
            MEM_rd         <= EX_rd;
            MEM_reg_write  <= EX_reg_write;
            MEM_mem_read   <= EX_mem_read;
            MEM_mem_write  <= EX_mem_write;
        end
    end

    // ============ STAGE 4: MEM (data memory) ============
    wire [31:0] mem_read_data;
    dmem u_dmem (.clk(clk), .mem_read(MEM_mem_read), .mem_write(MEM_mem_write),
        .addr(MEM_alu_result), .write_data(MEM_write_data),
        .read_data(mem_read_data));

    // ---- MEM/WB register ----
    reg [31:0] WB_alu_result, WB_mem_data;
    reg [4:0]  WB_rd;
    reg        WB_reg_write, WB_mem_read;
    always @(posedge clk or negedge rst_n) begin
        if (!rst_n) begin
            WB_reg_write<=0; WB_rd<=0; WB_alu_result<=0;
            WB_mem_data<=0; WB_mem_read<=0;
        end else begin
            WB_alu_result <= MEM_alu_result;
            WB_mem_data   <= mem_read_data;
            WB_rd         <= MEM_rd;
            WB_reg_write  <= MEM_reg_write;
            WB_mem_read   <= MEM_mem_read;
        end
    end

    // ============ STAGE 5: WB ============
    // load -> use memory data; otherwise -> use ALU result
    assign wb_data_out = WB_mem_read ? WB_mem_data : WB_alu_result;
    assign wb_rd_out   = WB_rd;
    assign wb_we_out   = WB_reg_write;
endmodule

pipelined/tb/pipeline_cpu_tb.v
module pipeline_cpu_tb;
    reg clk, rst_n;
    wire [31:0] pc_out, wb_data_out;
    wire [4:0]  wb_rd_out;
    wire        wb_we_out;

    pipeline_cpu dut (.clk(clk), .rst_n(rst_n),
        .pc_out(pc_out), .wb_data_out(wb_data_out),
        .wb_rd_out(wb_rd_out), .wb_we_out(wb_we_out));

    always #5 clk = ~clk;

    initial begin
        $dumpfile("pipeline_cpu.vcd");
        $dumpvars(0, pipeline_cpu_tb);
        clk = 0; rst_n = 0;
        #10 rst_n = 1;
        repeat (14) #10;

        $display("--- FINAL REGISTERS ---");
        $display("x1 = %0d (expect 100)", dut.u_rf.regs[1]);
        $display("x2 = %0d (expect 200)", dut.u_rf.regs[2]);
        $display("x3 = %0d (expect 5)",   dut.u_rf.regs[3]);
        $display("x4 = %0d (expect 205)", dut.u_rf.regs[4]);
        $finish;
    end
endmodule

pipelined/pipeline_cpu.vcd
$date
	Sat Jun 20 09:46:29 2026
$end
$version
	Icarus Verilog
$end
$timescale
	1s
$end
$scope module pipeline_cpu_tb $end
$var wire 1 ! wb_we_out $end
$var wire 5 " wb_rd_out [4:0] $end
$var wire 32 # wb_data_out [31:0] $end
$var wire 32 $ pc_out [31:0] $end
$var reg 1 % clk $end
$var reg 1 & rst_n $end
$scope module dut $end
$var wire 1 ' bubble $end
$var wire 1 % clk $end
$var wire 32 ( if_instr [31:0] $end
$var wire 32 ) pc_out [31:0] $end
$var wire 1 & rst_n $end
$var wire 5 * wb_rd_out [4:0] $end
$var wire 1 ! wb_we_out $end
$var wire 32 + wb_data_out [31:0] $end
$var wire 1 , stall $end
$var wire 32 - pc_next [31:0] $end
$var wire 32 . mem_read_data [31:0] $end
$var wire 32 / id_rs2_data [31:0] $end
$var wire 5 0 id_rs2 [4:0] $end
$var wire 32 1 id_rs1_data [31:0] $end
$var wire 5 2 id_rs1 [4:0] $end
$var wire 1 3 id_reg_write $end
$var wire 5 4 id_rd [4:0] $end
$var wire 7 5 id_opcode [6:0] $end
$var wire 1 6 id_mem_write $end
$var wire 1 7 id_mem_read $end
$var wire 2 8 id_imm_type [1:0] $end
$var wire 32 9 id_imm [31:0] $end
$var wire 1 : id_funct7_5 $end
$var wire 1 ; id_branch $end
$var wire 1 < id_alu_src $end
$var wire 4 = id_alu_op [3:0] $end
$var wire 2 > forward_b [1:0] $end
$var wire 2 ? forward_a [1:0] $end
$var wire 1 @ ex_zero $end
$var wire 32 A ex_b_pre [31:0] $end
$var wire 32 B ex_alu_result [31:0] $end
$var wire 32 C ex_alu_b [31:0] $end
$var wire 32 D ex_a [31:0] $end
$var reg 4 E EX_alu_op [3:0] $end
$var reg 1 F EX_alu_src $end
$var reg 32 G EX_imm [31:0] $end
$var reg 1 H EX_mem_read $end
$var reg 1 I EX_mem_write $end
$var reg 5 J EX_rd [4:0] $end
$var reg 1 K EX_reg_write $end
$var reg 5 L EX_rs1 [4:0] $end
$var reg 32 M EX_rs1_data [31:0] $end
$var reg 5 N EX_rs2 [4:0] $end
$var reg 32 O EX_rs2_data [31:0] $end
$var reg 32 P ID_instr [31:0] $end
$var reg 32 Q ID_pc [31:0] $end
$var reg 32 R MEM_alu_result [31:0] $end
$var reg 1 S MEM_mem_read $end
$var reg 1 T MEM_mem_write $end
$var reg 5 U MEM_rd [4:0] $end
$var reg 1 V MEM_reg_write $end
$var reg 32 W MEM_write_data [31:0] $end
$var reg 32 X WB_alu_result [31:0] $end
$var reg 32 Y WB_mem_data [31:0] $end
$var reg 1 Z WB_mem_read $end
$var reg 5 [ WB_rd [4:0] $end
$var reg 1 \ WB_reg_write $end
$var reg 32 ] pc [31:0] $end
$scope module u_alu $end
$var wire 32 ^ a [31:0] $end
$var wire 4 _ alu_op [3:0] $end
$var wire 32 ` b [31:0] $end
$var wire 1 @ zero $end
$var reg 32 a result [31:0] $end
$upscope $end
$scope module u_ctrl $end
$var wire 7 b opcode [6:0] $end
$var reg 1 < alu_src $end
$var reg 1 ; branch $end
$var reg 2 c imm_type [1:0] $end
$var reg 1 7 mem_read $end
$var reg 1 6 mem_write $end
$var reg 1 3 reg_write $end
$upscope $end
$scope module u_dmem $end
$var wire 32 d addr [31:0] $end
$var wire 1 % clk $end
$var wire 1 S mem_read $end
$var wire 1 T mem_write $end
$var wire 32 e write_data [31:0] $end
$var wire 32 f read_data [31:0] $end
$var integer 32 g i [31:0] $end
$upscope $end
$scope module u_fwd $end
$var wire 5 h ex_rs1 [4:0] $end
$var wire 5 i ex_rs2 [4:0] $end
$var wire 5 j mem_rd [4:0] $end
$var wire 1 V mem_reg_write $end
$var wire 5 k wb_rd [4:0] $end
$var wire 1 \ wb_reg_write $end
$var reg 2 l forward_a [1:0] $end
$var reg 2 m forward_b [1:0] $end
$upscope $end
$scope module u_hz $end
$var wire 1 H ex_mem_read $end
$var wire 5 n ex_rd [4:0] $end
$var wire 5 o id_rs1 [4:0] $end
$var wire 5 p id_rs2 [4:0] $end
$var reg 1 , stall $end
$upscope $end
$scope module u_imm $end
$var wire 3 q imm_type [2:0] $end
$var wire 32 r instr [31:0] $end
$var reg 32 s imm [31:0] $end
$upscope $end
$scope module u_rf $end
$var wire 1 % clk $end
$var wire 5 t ra1 [4:0] $end
$var wire 5 u ra2 [4:0] $end
$var wire 5 v wa [4:0] $end
$var wire 32 w wd [31:0] $end
$var wire 1 ! we $end
$var wire 32 x rd2 [31:0] $end
$var wire 32 y rd1 [31:0] $end
$upscope $end
$upscope $end
$upscope $end
$enddefinitions $end
$comment Show the parameter values. $end
$dumpall
$end
#0
$dumpvars
b0 y
b0 x
b0 w
b0 v
b0 u
b0 t
b0 s
b10011 r
b0 q
b0 p
b0 o
b0 n
b0 m
b0 l
b0 k
b0 j
b0 i
b0 h
b1000000 g
b0 f
b0 e
b0 d
b0 c
b10011 b
b0 a
b0 `
b0 _
b0 ^
b0 ]
0\
b0 [
0Z
b0 Y
b0 X
b0 W
0V
b0 U
0T
0S
b0 R
b0 Q
b10011 P
b0 O
b0 N
b0 M
b0 L
0K
b0 J
0I
0H
b0 G
0F
b0 E
b0 D
b0 C
b0 B
b0 A
1@
b0 ?
b0 >
b0 =
1<
0;
0:
b0 9
b0 8
07
06
b10011 5
b0 4
13
b0 2
b0 1
b0 0
b0 /
b0 .
b100 -
0,
b0 +
b0 *
b0 )
b10000010000011 (
0'
0&
0%
b0 $
b0 #
b0 "
0!
$end
#5
1%
#10
0%
1&
#15
17
1<
13
b100001000000100110011 (
b11 5
b11 b
b1 4
b1000 -
b100 $
b100 )
b100 ]
b10000010000011 P
b10000010000011 r
1K
1F
1%
#20
0%
#25
07
0<
13
bx 1
bx y
bx /
bx x
1'
1,
b110011 5
b110011 b
b1 2
b1 o
b1 t
b1 0
b1 p
b1 u
b10 4
b1 9
b1 s
b10100000000000110010011 (
1V
1H
b1 J
b1 n
b100001000000100110011 P
b100001000000100110011 r
b100 Q
b1100 -
b1000 $
b1000 )
b1000 ]
1%
#30
0%
#35
0'
0,
b1100100 .
b1100100 f
b10 >
b10 m
b10 ?
b10 l
0H
0K
0F
b1 N
b1 i
b1 L
b1 h
b10 J
b10 n
b1 G
bx O
bx M
1S
b1 U
b1 j
1!
1\
1%
#40
0%
#45
b1100100 C
b1100100 `
0@
b11001000 B
b11001000 a
b1100100 A
b1100100 D
b1100100 ^
1<
13
b0 1
b0 y
b1100100 #
b1100100 +
b1100100 w
b0 .
b0 f
b1 >
b1 m
b1 ?
b1 l
b10011 5
b10011 b
b0 2
b0 o
b0 t
b101 0
b101 p
b101 u
b11 4
b101 9
b101 s
b1100010000001000110011 (
1Z
b1 "
b1 *
b1 v
b1 [
b1 k
b1100100 Y
0S
0V
b10 U
b10 j
1K
b10100000000000110010011 P
b10100000000000110010011 r
b1000 Q
b10000 -
b1100 $
b1100 )
b1100 ]
1%
#50
0%
#55
bx A
b0 D
b0 ^
0<
13
bx 1
bx y
b101 B
b101 a
b0 (
b110011 5
b110011 b
b10 2
b10 o
b10 t
b11 0
b11 p
b11 u
b100 4
b11 9
b11 s
b101 C
b101 `
b0 >
b0 m
b0 ?
b0 l
b0 #
b0 +
b0 w
b10100 -
b10000 $
b10000 )
b10000 ]
b1100010000001000110011 P
b1100010000001000110011 r
b1100 Q
1F
b101 N
b101 i
b0 L
b0 h
b11 J
b11 n
b101 G
b0 M
1V
b1100100 W
b1100100 e
b11001000 R
b11001000 d
0Z
0!
0\
b10 "
b10 *
b10 v
b10 [
b10 k
b0 Y
1%
#60
0%
#65
b101 A
0@
b11001101 B
b11001101 a
b11001000 D
b11001000 ^
03
b0 1
b0 y
b0 /
b0 x
b11001000 #
b11001000 +
b11001000 w
b10 >
b10 m
b1 ?
b1 l
b101 C
b101 `
b0 5
b0 b
b0 2
b0 o
b0 t
b0 0
b0 p
b0 u
b0 4
b0 9
b0 s
bx (
1!
1\
b11001000 X
b11 U
b11 j
bx W
bx e
b101 R
b101 d
0F
b11 N
b11 i
b10 L
b10 h
b100 J
b100 n
b11 G
bx M
b0 P
b0 r
b10000 Q
b11000 -
b10100 $
b10100 )
b10100 ]
1%
#70
0%
#75
b0x =
1@
b0 B
b0 a
b0 D
b0 ^
bx 1
bx y
bx /
bx x
b0 C
b0 `
bx 5
bx b
bx 2
bx o
bx t
bx 0
bx p
bx u
bx 4
x:
bx 9
bx s
b0 A
b0 >
b0 m
b0 ?
b0 l
b101 #
b101 +
b101 w
b11100 -
b11000 $
b11000 )
b11000 ]
bx P
bx r
b10100 Q
0K
b0 N
b0 i
b0 L
b0 h
b0 J
b0 n
b0 G
b0 O
b0 M
b100 U
b100 j
b101 W
b101 e
b11001101 R
b11001101 d
b11 "
b11 *
b11 v
b11 [
b11 k
b101 X
1%
#80
0%
#85
bx C
bx `
bx A
bx D
bx ^
b11001101 #
b11001101 +
b11001101 w
b100 "
b100 *
b100 v
b100 [
b100 k
b11001101 X
0V
b0 U
b0 j
b0 W
b0 e
b0 R
b0 d
b0x E
b0x _
bx N
bx i
bx L
bx h
bx J
bx n
bx G
bx O
bx M
b11000 Q
b100000 -
b11100 $
b11100 )
b11100 ]
1%
#90
0%
#95
b0 #
b0 +
b0 w
b100100 -
b100000 $
b100000 )
b100000 ]
b11100 Q
bx U
bx j
bx W
bx e
0!
0\
b0 "
b0 *
b0 v
b0 [
b0 k
b0 X
1%
#100
0%
#105
bx "
bx *
bx v
bx [
bx k
b100000 Q
b101000 -
b100100 $
b100100 )
b100100 ]
1%
#110
0%
#115
b101100 -
b101000 $
b101000 )
b101000 ]
b100100 Q
1%
#120
0%
#125
b101000 Q
b110000 -
b101100 $
b101100 )
b101100 ]
1%
#130
0%
#135
b110100 -
b110000 $
b110000 )
b110000 ]
b101100 Q
1%
#140
0%
#145
b110000 Q
b111000 -
b110100 $
b110100 )
b110100 ]
1%
